{
    "nixpkgs": {
        "branch": "nixos-unstable-small",
        "description": "Nix Packages collection",
        "homepage": "",
        "owner": "NixOS",
        "repo": "nixpkgs",
        "rev": "10ce023e3d9c49111a05acb42930535b9d43097d",
        "sha256": "1nja06dibv76md8b5rpz6mmydx2f4537dcflar6npg3x33s9qwcp",
        "type": "tarball",
        "url": "https://github.com/NixOS/nixpkgs/archive/10ce023e3d9c49111a05acb42930535b9d43097d.tar.gz",
        "url_template": "https://github.com/<owner>/<repo>/archive/<rev>.tar.gz"
    },
    "pre-commit-hooks": {
        "branch": "master",
        "description": "Seamless integration of https://pre-commit.com git hooks with Nix.",
        "homepage": "",
        "owner": "cachix",
        "repo": "pre-commit-hooks.nix",
        "rev": "397f0713d007250a2c7a745e555fa16c5dc8cadb",
        "sha256": "0hjbq4pf8a2qdndx0xdb3yjhx9l3l5grk4mlk78vw4zm32fgyrq2",
        "type": "tarball",
        "url": "https://github.com/cachix/pre-commit-hooks.nix/archive/397f0713d007250a2c7a745e555fa16c5dc8cadb.tar.gz",
        "url_template": "https://github.com/<owner>/<repo>/archive/<rev>.tar.gz"
    }
}
